protobuf_schematics/__init__.py
protobuf_schematics/cli.py
protobuf_schematics/engine.py
protobuf_schematics/filters.py
protobuf_schematics/models.py
protobuf_schematics/types.py
protobuf_schematics/templates/schematics_py.tmpl
protobuf_schematics-0.4.1.dist-info/LICENSE
protobuf_schematics-0.4.1.dist-info/METADATA
protobuf_schematics-0.4.1.dist-info/WHEEL
protobuf_schematics-0.4.1.dist-info/entry_points.txt
protobuf_schematics-0.4.1.dist-info/top_level.txt
protobuf_schematics-0.4.1.dist-info/RECORD
