Metadata-Version: 1.1
Name: protobuf_schematics
Version: 0.4.1
Summary: Convert ProtoBuf proto file to cute Schematics classes file
Home-page: https://github.com/AlmogCohen/protobuf-schematics
Author: Almog Cohen
Author-email: UNKNOWN
License: Apache Software License 2.0
Keywords: protobuf_schematics
Platform: UNKNOWN
Classifier: Intended Audience :: Developers
Classifier: License :: OSI Approved :: Apache Software License
Classifier: Natural Language :: English
Classifier: Programming Language :: Python :: 2
Classifier: Programming Language :: Python :: 2.7
Classifier: Programming Language :: Python :: 3
Classifier: Programming Language :: Python :: 3.4
Classifier: Programming Language :: Python :: 3.5
Classifier: Programming Language :: Python :: 3.6
